MANIFEST.in
README.rst
setup.py
silleoscns/LICENSE
silleoscns/installguide.md
silleoscns/readme.md
silleoscns/userguide.md
silleoscns.egg-info/PKG-INFO
silleoscns.egg-info/SOURCES.txt
silleoscns.egg-info/dependency_links.txt
silleoscns.egg-info/top_level.txt
silleoscns/.git/HEAD
silleoscns/.git/config
silleoscns/.git/description
silleoscns/.git/index
silleoscns/.git/packed-refs
silleoscns/.git/hooks/applypatch-msg.sample
silleoscns/.git/hooks/commit-msg.sample
silleoscns/.git/hooks/fsmonitor-watchman.sample
silleoscns/.git/hooks/post-update.sample
silleoscns/.git/hooks/pre-applypatch.sample
silleoscns/.git/hooks/pre-commit.sample
silleoscns/.git/hooks/pre-merge-commit.sample
silleoscns/.git/hooks/pre-push.sample
silleoscns/.git/hooks/pre-rebase.sample
silleoscns/.git/hooks/pre-receive.sample
silleoscns/.git/hooks/prepare-commit-msg.sample
silleoscns/.git/hooks/push-to-checkout.sample
silleoscns/.git/hooks/update.sample
silleoscns/.git/info/exclude
silleoscns/.git/logs/HEAD
silleoscns/.git/logs/refs/heads/master
silleoscns/.git/logs/refs/remotes/origin/HEAD
silleoscns/.git/objects/pack/pack-d117e15003ffb11aa236e1f427632345d0c3a337.idx
silleoscns/.git/objects/pack/pack-d117e15003ffb11aa236e1f427632345d0c3a337.pack
silleoscns/.git/refs/heads/master
silleoscns/.git/refs/remotes/origin/HEAD
silleoscns/pics/coords_sys_at_t0.png
silleoscns/pics/gui_ex.png
silleoscns/pics/p_8_i_45_.gif
silleoscns/pics/plane_numbering.png
silleoscns/pics/satellite_intra_plane_numbering.png
silleoscns/source/city_data.txt
silleoscns/source/constellation.py
silleoscns/source/gui.py
silleoscns/source/simulation.py
silleoscns/source/__pycache__/constellation.cpython-310.pyc
silleoscns/source/__pycache__/constellation.cpython-36.pyc
silleoscns/source/__pycache__/simulation.cpython-310.pyc
silleoscns/source/__pycache__/simulation.cpython-36.pyc