Metadata-Version: 2.1
Name: silleoscns
Version: 0.1
Summary: Walker Comm Simulation
Author: Ben Kempton
License: GNU General Public License Version 3, [1] B. S. Kempton, "A Simulation Tool to Study Routing in Large Broadband Satellite Networks." Christopher Newport University, 2020.
Keywords: Walker Comm Sim
Classifier: Development Status :: 3 - Alpha
Classifier: Intended Audience :: Developers
Classifier: Topic :: Software Development :: Build Tools
Classifier: License :: OSI Approved :: MIT License
Classifier: Programming Language :: Python :: 3.6
